{
  "Авария / Водоотведение": [
    "потек унитаз",
    "труба канализации",
    "воняет из канализации",
    "флюгарка",
    "канализационная труба",
    "бежит канализация",
    "из канализации течет",
    "унитаз",
    "пахнет канализацией",
    "канализация топит",
    "водоотведение",
    "вода в унитазе",
    "туалет",
    "прорвало канализацию",
    "течь канализации",
    "канализация",
    "канализация затапливает",
    "вонь из канализации",
    "запах из подвала",
    "запах из канализации"
  ],
  "Авария / Водоснабжение": [
    "люк открыт",
    "перекрыть воду",
    "открыть воду",
    "течет труба",
    "счетчик воды капает",
    "прорвало трубопровод",
    "кран бежит",
    "вода льется",
    "хлещет вода",
    "воды",
    "прорвало трубу",
    "топлю соседей",
    "капает",
    "нет воды",
    "общий стояк",
    "кран",
    "вода",
    "горячей воды",
    "водоснабжение",
    "топит",
    "вода вытекает из под земли",
    "потек душ",
    "топим",
    "заливаю соседей",
    "колодец",
    "вода течет",
    "в подъезде течет вода",
    "льет с потолка",
    "замена труб",
    "у колодца люк открыт",
    "подтекает",
    "люк провалился",
    "топлю соседа",
    "хвс",
    "вода хлещет из под земли",
    "трубу прорвало",
    "вода течет из под земли",
    "порыв воды",
    "течет в стык",
    "холодная вода",
    "потекла вода",
    "труба",
    "вода бежит",
    "вода хлещет",
    "холодной воды",
    "вода еле течет",
    "проблема с водой",
    "прорыв трубопровода",
    "топят",
    "счетчик воды протекает",
    "водопровод",
    "течет вода",
    "потекла труба",
    "топлю соседку",
    "вода капает",
    "льется вода",
    "вода течет по улице",
    "давление воды",
    "с потолка",
    "стояк течет",
    "потоп",
    "утечка воды",
    "прорвало",
    "стояк потек",
    "вода течет из колодца",
    "труба течет",
    "течь",
    "льет вода",
    "бежит кран",
    "бежит вода",
    "затапливаю соседа",
    "затопили",
    "заливают",
    "сантехник",
    "топит сверху",
    "вода течет из под люка",
    "заливает",
    "пробило стояк",
    "гвс",
    "колонка бежит",
    "прорыв трубы",
    "затопило квартиру",
    "затопило колодец",
    "колодец провалился",
    "горячая вода",
    "водонагреватель",
    "кипяток",
    "воды нет",
    "заменить трубы",
    "сорвало кран",
    "затапливают",
    "залили соседи",
    "течет",
    "течет в ванной",
    "в ванной течет",
    "течет в туалете",
    "в туалете течет"
  ],
  "Авария / Засор водоотведения": [
    "забился унитаз",
    "прочистить колодец",
    "забита канализация",
    "засорился колодец",
    "засорилась канализация",
    "почистить колодец",
    "засор канализации",
    "засор водоотведения",
    "засор трубы",
    "забило трубу",
    "забилась канализация",
    "засор колодца",
    "засор в туалете",
    "засор в ванной",
    "засор ванны"
  ],
  "Авария / Засор мусоропровода": [
    "мусоропровод",
    "засор мусоропровода"
  ],
  "Авария / Отопление": [
    "отопление",
    "батареи холодные",
    "подтекает батарея",
    "нет отопления",
    "батарея течет",
    "радиатор",
    "батарея",
    "течь из батареи",
    "холодно в квартире",
    "холодно дома",
    "отопления",
    "холодное отопление",
    "трубы отопления",
    "батареи",
    "труба отопления",
    "холодно"
  ],
  "Авария / Пожарная сигнализация": [
    "пожар",
    "пожарные",
    "пожарная сигнализация",
    "горит"
  ],
  "Авария / Электроснабжение": [
    "не горит свет",
    "электрика",
    "свет",
    "током стукнуло",
    "не работает освещение",
    "обесточен",
    "не работают розетки",
    "не работает свет",
    "провод",
    "предохранители",
    "нет света",
    "силовой кабель",
    "пробки",
    "пробку",
    "автомат",
    "удар током",
    "электроснабжение",
    "проводка",
    "линии электропередач",
    "вырубило автомат",
    "провода",
    "освещение",
    "искры",
    "электричество",
    "пропало электричество",
    "отключили свет",
    "электропотребление",
    "электроэнергия",
    "света нет",
    "электрик",
    "замкнуло проводку",
    "замыкание",
    "нет электричества",
    "нету света",
    "света нету",
    "бьет током",
    "розетки",
    "нет освещения",
    "свет не горит"
  ],
  "Авария / Крыша": [
    "сливная труба",
    "протечка кровли",
    "крыша",
    "сорвало крышу",
    "протекла кровля",
    "кровля",
    "течет крыша"
  ],
  "Авария / Газ": [
    "газ",
    "газовое снабжение",
    "нет газа"
  ],
  "Текущая / Бухгалтерия": [
    "показания счетчиков",
    "сверить показания",
    "вопрос по квитанции",
    "проверить показания счётчика",
    "платёжка",
    "оплата",
    "показания",
    "счётчики передать",
    "счетчики передать",
    "показания счётчиков",
    "передать показания",
    "бухгалтерию",
    "начисления",
    "квартплата",
    "бухгалтерия",
    "квитанция",
    "неправильно взяли плату",
    "выписка из домовой книги",
    "справка о составе семьи",
    "субсидия",
    "нотариус",
    "развод",
    "молодая семья",
    "детские",
    "детский сад",
    "школа",
    "стипендия",
    "льготы",
    "алименты",
    "молочная кухня",
    "смена паспорта",
    "опеку",
    "усыновление",
    "в суд",
    "справка о задолженности",
    "лицевой счет",
    "справка об оплате",
    "мне нужна бухгалтерия",
    "с бухгалтером"
  ],
  "Текущая / Вентиляция": [
    "запах канализации",
    "конденсат",
    "запах в туалете",
    "запах из раковины",
    "запотевание окон",
    "запотевают окна"
  ],
  "Текущая / Водоснабжение": [
    "температура воды не соответствует",
    "счетчик воды",
    "змеевик",
    "проверить показания счетчика в колодце",
    "заменить смеситель",
    "заменить счетчик воды",
    "горячая вода не соответствует",
    "протечка счетчика",
    "замена смесителя",
    "поменять смеситель",
    "смеситель",
    "поменять кран",
    "бойлер",
    "полотенцесушитель",
    "полотенце",
    "счетчики водяные",
    "водяные счетчики",
    "пломбировать счетчики водяные",
    "заменить счетчик горячей воды"
  ],
  "Текущая / Вывоз мусора": [
    "вывезти мусор",
    "вывоз мусора"
  ],
  "Текущая / Домофоны": [
    "домофон",
    "сломан доводчик",
    "сломался доводчик",
    "доводчик"
  ],
  "Текущая / Засор водоотведения": [
    "забит унитаз",
    "не уходит вода"
  ],
  "Текущая / Иное": [
    "ворота",
    "водосточная труба",
    "время работы",
    "сломали дверь",
    "слесарь",
    "связаться с директором",
    "трава у дома",
    "печная труба",
    "голуби",
    "сломалось окно",
    "шлагбаум",
    "соедините с директором",
    "паркинг",
    "разбили окно",
    "окно",
    "вентиляция",
    "окно выпало",
    "магнит",
    "не работают ворота",
    "интернет",
    "сломалась дверь",
    "дверь",
    "невозможно дозвониться",
    "не работает замок",
    "дерево",
    "спил деревьев"
  ],
  "Текущая / Лифты": [
    "лифт",
    "застревание",
    "застрял",
    "застряли"
  ],
  "Текущая / Ремонт": [
    "промерзает стена",
    "ремонт швов",
    "дует из угла",
    "дует с угла",
    "течь кровли",
    "протечка крыши",
    "течь козырька",
    "течь балкона",
    "плесень",
    "ремонт крыльца",
    "ремонт козырька",
    "почтовые ящики",
    "ремонт подъезда"
  ],
  "Текущая / Слесарные работы": [
    "замена счетчиков",
    "опломбировка",
    "замена батареи",
    "замена полотенцесушителя",
    "хомут на стояке",
    "счетчик",
    "счетчики",
    "опломбировать счетчик",
    "заменить счетчик",
    "заменили счетчик",
    "поменять счетчик",
    "сломался счетчик",
    "опломбировать"
  ],
  "Текущая / Уборка внутренняя": [
    "грязный пол",
    "грязь в подъезде",
    "убирают в подъезде",
    "уборка в подъезде",
    "пол",
    "уборщик",
    "мусор на лестничной площадке",
    "уборщица",
    "уборка помещений"
  ],
  "Текущая / Уборка уличная": [
    "снег на крыльце",
    "дворник",
    "крыльцо",
    "грязь на улице",
    "грязь у подъезда",
    "уборка во дворе",
    "снег во дворе",
    "убирают двор",
    "убирают во дворе",
    "лед",
    "чистка снега",
    "чистка дороги"
  ],
  "Текущая / Электроснабжение": [
    "нет света в подъезде",
    "свет в подъезде",
    "на площадке не горит свет",
    "не работает плита электрическая",
    "лампа",
    "в подъезде нет света",
    "на площадке нет света",
    "на площадке не горит лампа",
    "нет освещения на лестничной клетке",
    "освещение подъезда",
    "сломалась розетка",
    "в подъезде не горит свет",
    "перегорел свет",
    "лампочка",
    "счетчик электричества"
  ],
  "Текущая / Антенна": [
    "нет сигнала",
    "не работает антенна",
    "антенна",
    "не работает телевизор",
    "сигнала нет",
    "телевизор не работает",
    "телевизор не показывает",
    "антенна не ловит",
    "не ловит сигнал",
    "сигнал не ловит"
  ],
  "Санобработка": [
    "дезинсекция",
    "потравить муравьев",
    "потравить комаров",
    "потравить насекомых",
    "муравьи",
    "комары",
    "насекомые",
    "дезинфекция",
    "дератизация",
    "потравить мышей",
    "потравить крыс",
    "бегают мыши",
    "бегают крысы",
    "мыши",
    "крысы"
  ]
}